{
  "id": "51063b0f-6e2a-402b-a47b-159c83675392",
  "runtime": "bash",
  "purpose": "Verify S02 codebase state",
  "script_chars": 859,
  "started_at": "2026-05-06T06:04:52.126Z",
  "finished_at": "2026-05-06T06:04:52.128Z",
  "exit_code": -4058,
  "signal": null,
  "timed_out": false,
  "duration_ms": 2,
  "stdout_bytes": 0,
  "stderr_bytes": 31,
  "stdout_truncated": false,
  "stderr_truncated": false,
  "stdout_path": "D:\\TraSua\\.gsd\\exec\\51063b0f-6e2a-402b-a47b-159c83675392.stdout",
  "stderr_path": "D:\\TraSua\\.gsd\\exec\\51063b0f-6e2a-402b-a47b-159c83675392.stderr"
}
