{
  "id": "ba830926-74c9-45ed-8d8f-c45e9b376f94",
  "runtime": "bash",
  "purpose": "Explore table/QR codebase state",
  "script_chars": 1013,
  "started_at": "2026-05-06T09:20:09.619Z",
  "finished_at": "2026-05-06T09:20:09.623Z",
  "exit_code": -4058,
  "signal": null,
  "timed_out": false,
  "duration_ms": 4,
  "stdout_bytes": 0,
  "stderr_bytes": 31,
  "stdout_truncated": false,
  "stderr_truncated": false,
  "stdout_path": "D:\\TraSua\\.gsd\\exec\\ba830926-74c9-45ed-8d8f-c45e9b376f94.stdout",
  "stderr_path": "D:\\TraSua\\.gsd\\exec\\ba830926-74c9-45ed-8d8f-c45e9b376f94.stderr"
}
